qpt/RELEASE
qpt/__init__.py
qpt/_compatibility.py
qpt/command.py
qpt/executor.py
qpt/run.py
qpt/smart_opt.py
qpt/sys_info.py
qpt/version.py
qpt/__pycache__/__init__.cpython-39.pyc
qpt/__pycache__/_compatibility.cpython-39.pyc
qpt/__pycache__/executor.cpython-39.pyc
qpt/__pycache__/sys_info.cpython-39.pyc
qpt/__pycache__/version.cpython-39.pyc
qpt/ext/compile/7z/7z.exe
qpt/ext/compile/7z/sfx/7zsd_All_x64.sfx
qpt/ext/ico/Logo.ico
qpt/ext/launcher/Main.exe
qpt/ext/launcher/compatibility_mode.cmd
qpt/ext/launcher/configs/Logo.ico
qpt/ext/launcher/configs/README.TXT
qpt/ext/launcher/configs/收集Debug信息.cmd
qpt/ext/launcher_debug/Debug-打印已安装的软件包列表.cmd
qpt/ext/launcher_debug/Debug-收集Debug信息.cmd
qpt/ext/launcher_debug/Debug-进入Python环境.cmd
qpt/ext/launcher_debug/Debug-进入半虚拟环境.cmd
qpt/ext/launcher_debug/Debug.exe
qpt/ext/launcher_debug/compatibility_mode.cmd
qpt/ext/launcher_debug/configs/Logo.ico
qpt/ext/launcher_entry/entry_debug.cmd
qpt/ext/launcher_entry/entry_run.cmd
qpt/ext/launcher_entry/entry_run_hidden.cmd
qpt/gui/GUI_module_launcher.py
qpt/gui/GUI_unzip.py
qpt/gui/qpt_about.py
qpt/gui/qpt_choose_env.py
qpt/gui/qpt_msg.py
qpt/gui/qpt_run_gui.py
qpt/gui/qpt_start.py
qpt/gui/qpt_unzip.py
qpt/kernel/__init__.py
qpt/kernel/__pycache__/__init__.cpython-39.pyc
qpt/kernel/mfc/progress_bar.py
qpt/kernel/qpt_clr/__init__.py
qpt/kernel/qpt_clr/progressbar.py
qpt/kernel/qt_ui/GDMAdmin.ui
qpt/kernel/qt_ui/GDMLauncher_dialog.ui
qpt/kernel/qt_ui/__init__.py
qpt/kernel/qt_ui/mini_about.py
qpt/kernel/qt_ui/mini_about.ui
qpt/kernel/qt_ui/unzip.py
qpt/kernel/qt_ui/unzip.ui
qpt/kernel/qt_ui/welcome.py
qpt/kernel/qt_ui/welcome.ui
qpt/kernel/tools/__init__.py
qpt/kernel/tools/_qpt_venv.py
qpt/kernel/tools/_sys_tools.py
qpt/kernel/tools/interpreter.py
qpt/kernel/tools/log_op.py
qpt/kernel/tools/os_op.py
qpt/kernel/tools/terminal.py
qpt/kernel/tools/__pycache__/__init__.cpython-39.pyc
qpt/kernel/tools/__pycache__/interpreter.cpython-39.pyc
qpt/kernel/tools/__pycache__/log_op.cpython-39.pyc
QPT-1.0a9.dev2.dist-info/LICENSE
QPT-1.0a9.dev2.dist-info/METADATA
QPT-1.0a9.dev2.dist-info/WHEEL
QPT-1.0a9.dev2.dist-info/entry_points.txt
QPT-1.0a9.dev2.dist-info/top_level.txt
QPT-1.0a9.dev2.dist-info/RECORD
