Metadata-Version: 2.1
Name: QPT
Version: 1.0a9.dev2
Summary: QPT-基于Python的快捷环境封装工具
Home-page: https://github.com/GT-ZhangAcer/QPT
Author: GT-ZhangAcer
Author-email: zhangacer@foxmail.com
License: LGPL
Platform: UNKNOWN
Requires-Python: >3.5
License-File: LICENSE
Requires-Dist: wget
Requires-Dist: click
